nums_Sdela/__init__.py
nums_Sdela/funciones.py
nums_sdela-0.1.5.dist-info/METADATA
nums_sdela-0.1.5.dist-info/WHEEL
nums_sdela-0.1.5.dist-info/top_level.txt
nums_sdela-0.1.5.dist-info/RECORD
