Metadata-Version: 2.4
Name: nums_Sdela
Version: 0.1.5
Summary: Librería educativa para jugar con números: factorial, invertir, pasar a binario y los n términos de la serie Fibonacci.
Author: Dela
Requires-Python: >=3.8
